tgb/datasets/ICEWS14/ent2word.py
tgb/datasets/ICEWS14/icews14.py
tgb/datasets/dataset_scripts/MAG/mag.py
tgb/datasets/dataset_scripts/MAG/old/plot_stats.py
tgb/datasets/dataset_scripts/dgraph.py
tgb/datasets/dataset_scripts/dgraph_Readme.md
tgb/datasets/dataset_scripts/process_arxiv.py
tgb/datasets/dataset_scripts/process_github.py
tgb/datasets/dataset_scripts/tgbl-coin.py
tgb/datasets/dataset_scripts/tgbl-coin_neg_generator.py
tgb/datasets/dataset_scripts/tgbl-comment.py
tgb/datasets/dataset_scripts/tgbl-comment_neg_generator.py
tgb/datasets/dataset_scripts/tgbl-flight.py
tgb/datasets/dataset_scripts/tgbl-flight_neg_generator.py
tgb/datasets/dataset_scripts/tgbl-review.py
tgb/datasets/dataset_scripts/tgbl-review_neg_generator.py
tgb/datasets/dataset_scripts/tgbl-wiki_neg_generator.py
tgb/datasets/dataset_scripts/tgbn-genre.py
tgb/datasets/dataset_scripts/tgbn-reddit.py
tgb/datasets/dataset_scripts/tgbn-token.py
tgb/datasets/dataset_scripts/tgbn-trade.py
tgb/datasets/tgbl_enron/tgbl-enron_neg_generator.py
tgb/datasets/tgbl_enron/tgbl_enron.py
tgb/datasets/tgbl_lastfm/tgbl-lastfm_neg_generator.py
tgb/datasets/tgbl_subreddit/tgbl-subreddit_neg_generator.py
tgb/datasets/tgbl_uci/tgbl-uci_neg_generator.py
tgb/datasets/tgbl_uci/tgbl_uci.py
tgb/datasets/thgl_forum/merge_files.py
tgb/datasets/thgl_forum/num_edges_discretized_thgl-forum.png
tgb/datasets/thgl_forum/thgl-forum.py
tgb/datasets/thgl_forum/thgl_forum_ns_gen.py
tgb/datasets/thgl_github/2024_01/github_extract.py
tgb/datasets/thgl_github/2024_02/github_extract.py
tgb/datasets/thgl_github/2024_03/github_extract.py
tgb/datasets/thgl_github/extract_subset.py
tgb/datasets/thgl_github/thgl_github.py
tgb/datasets/thgl_github/thgl_github_ns_gen.py
tgb/datasets/thgl_myket/thgl_myket.py
tgb/datasets/thgl_myket/thgl_myket_ns_gen.py
tgb/datasets/thgl_software/thgl_software.py
tgb/datasets/thgl_software/thgl_software_ns_gen.py
tgb/datasets/tkgl_icews/tkgl_icews.py
tgb/datasets/tkgl_icews/tkgl_icews_ns_gen.py
py_tgb-2.1.0.dist-info/METADATA
py_tgb-2.1.0.dist-info/WHEEL
py_tgb-2.1.0.dist-info/RECORD
