Metadata-Version: 2.3
Name: py-tgb
Version: 2.1.0
Summary: Temporal Graph Benchmark project repo
Author: shenyang Huang
Author-email: shenyang.huang@mail.mcgill.ca
Requires-Python: >=3.9,<4.0
Classifier: Programming Language :: Python :: 3
Classifier: Programming Language :: Python :: 3.9
Classifier: Programming Language :: Python :: 3.10
Classifier: Programming Language :: Python :: 3.11
Classifier: Programming Language :: Python :: 3.12
Classifier: Programming Language :: Python :: 3.13
Requires-Dist: clint (>=0.5.1,<0.6.0)
Requires-Dist: numpy (>=2.0.2,<3.0.0)
Requires-Dist: pandas (>=2.2.3)
Requires-Dist: requests (>=2.28.2,<3.0.0)
Requires-Dist: scikit-learn (>=1.2.2,<2.0.0)
Requires-Dist: torch-geometric (>=2.3.0,<3.0.0)
Requires-Dist: tqdm (>=4.65.0,<5.0.0)
